README.md
setup.py
src/vdk/plugin/duckdb/duckdb_configuration.py
src/vdk/plugin/duckdb/duckdb_plugin.py
src/vdk/plugin/duckdb/ingest_to_duckdb.py
src/vdk_duckdb.egg-info/PKG-INFO
src/vdk_duckdb.egg-info/SOURCES.txt
src/vdk_duckdb.egg-info/dependency_links.txt
src/vdk_duckdb.egg-info/entry_points.txt
src/vdk_duckdb.egg-info/requires.txt
src/vdk_duckdb.egg-info/top_level.txt
tests/test_plugin.py